LICENSE
MANIFEST.in
README.rst
auth.cfg.default
setup.cfg
setup.py
docs/.DS_Store
docs/Makefile
docs/conf.py
docs/index.rst
docs/introduction.rst
docs/make.bat
docs/modules.rst
docs/requirements.txt
docs/twall.console.rst
docs/twall.rst
docs/twall.twitter.rst
docs/twall.web.rst
docs/usage_in_code.rst
tests/test_twitter.py
tests/test_webapp.py
tests/fixtures/fixtures.py
tests/fixtures/cassettes/twitter_cassette.json
tests/fixtures/cassettes/webapp_cassette.json
twall/__init__.py
twall/__main__.py
twall/settings.cfg
twall/twall.py
twall.egg-info/PKG-INFO
twall.egg-info/SOURCES.txt
twall.egg-info/dependency_links.txt
twall.egg-info/entry_points.txt
twall.egg-info/requires.txt
twall.egg-info/top_level.txt
twall/console/__init__.py
twall/console/console.py
twall/console/print_worker.py
twall/console/wall_worker.py
twall/twitter/__init__.py
twall/twitter/api.py
twall/web/__init__.py
twall/web/app.py
twall/web/twitter_adapter.py
twall/web/static/css/bootstrap.min.css
twall/web/static/css/wall.css
twall/web/static/fonts/glyphicons-halflings-regular.eot
twall/web/static/fonts/glyphicons-halflings-regular.svg
twall/web/static/fonts/glyphicons-halflings-regular.ttf
twall/web/static/fonts/glyphicons-halflings-regular.woff
twall/web/static/fonts/glyphicons-halflings-regular.woff2
twall/web/static/js/bootstrap.min.js
twall/web/static/js/jquery.min.js
twall/web/static/js/wall.js
twall/web/templates/tweets.html
twall/web/templates/wall.html