Metadata-Version: 1.1
Name: twall
Version: 0.5.1
Summary: Twitter Wall project for MI-PYT by Daniel Maly
Home-page: https://github.com/DanielMaly/twall
Author: Daniel Malý
Author-email: maly.dan@gmail.com
License: MIT
Keywords: twitter,search,wall
Platform: UNKNOWN
Classifier: Development Status :: 4 - Beta
Classifier: Environment :: Console
Classifier: Environment :: Web Environment
Classifier: Intended Audience :: End Users/Desktop
Classifier: Framework :: Flask
Classifier: Natural Language :: English
Classifier: Operating System :: MacOS :: MacOS X
Classifier: Operating System :: POSIX :: Linux
Classifier: Programming Language :: Python :: 3.5
Classifier: Programming Language :: Python :: Implementation :: CPython
Classifier: Programming Language :: Python :: 3 :: Only
Classifier: Topic :: Internet :: WWW/HTTP :: Dynamic Content
Classifier: License :: OSI Approved :: MIT License
